graph_segment/__init__.py
graph_segment/_core.cpython-310-x86_64-linux-gnu.so
graph_segment-0.0.2.dist-info/METADATA
graph_segment-0.0.2.dist-info/WHEEL
graph_segment-0.0.2.dist-info/RECORD
graph_segment-0.0.2.dist-info/licenses/LICENSE
